[
    {
        "name": "John Doe",
        "company": "YY Ventures",
        "country": "Bangladesh",
        "image": "https://i.ibb.co/WGh0qjK/yunus.jpg"
    },
    {
        "name": "John Doe",
        "company": "YY Ventures",
        "country": "Bangladesh",
        "image": "https://i.ibb.co/WGh0qjK/yunus.jpg"
    },
    {
        "name": "John Doe",
        "company": "YY Ventures",
        "country": "Bangladesh",
        "image": "https://i.ibb.co/WGh0qjK/yunus.jpg"
    },
    {
        "name": "John Doe",
        "company": "YY Ventures",
        "country": "Bangladesh",
        "image": "https://i.ibb.co/WGh0qjK/yunus.jpg"
    },
    {
        "name": "John Doe",
        "company": "YY Ventures",
        "country": "Egypt",
        "image": "https://i.ibb.co/WGh0qjK/yunus.jpg"
    },
    {
        "name": "John Doe",
        "company": "YY Ventures",
        "country": "Nepal",
        "image": "https://i.ibb.co/WGh0qjK/yunus.jpg"
    },
    {
        "name": "John Doe",
        "company": "YY Ventures",
        "country": "Nepal",
        "image": "https://i.ibb.co/WGh0qjK/yunus.jpg"
    },
    {
        "name": "John Doe",
        "company": "YY Ventures",
        "country": "India",
        "image": "https://i.ibb.co/WGh0qjK/yunus.jpg"
    }
]